kitconcept/__init__.py
kitconcept/core/__init__.py
kitconcept/core/_types.py
kitconcept/core/configure.zcml
kitconcept/core/dependencies.zcml
kitconcept/core/factory.py
kitconcept/core/interfaces.py
kitconcept/core/permissions.zcml
kitconcept/core/profiles.zcml
kitconcept/core/behaviors/__init__.py
kitconcept/core/behaviors/additional_contact_info.py
kitconcept/core/behaviors/blocks_settings.py
kitconcept/core/behaviors/configure.zcml
kitconcept/core/behaviors/person_bio.py
kitconcept/core/behaviors/person_image.py
kitconcept/core/content/__init__.py
kitconcept/core/controlpanel/__init__.py
kitconcept/core/controlpanel/configure.zcml
kitconcept/core/controlpanel/kitconcept.py
kitconcept/core/indexers/__init__.py
kitconcept/core/indexers/configure.zcml
kitconcept/core/locales/__init__.py
kitconcept/core/locales/__main__.py
kitconcept/core/locales/kitconcept.core.pot
kitconcept/core/locales/de/LC_MESSAGES/kitconcept.core.mo
kitconcept/core/locales/de/LC_MESSAGES/kitconcept.core.po
kitconcept/core/locales/en/LC_MESSAGES/kitconcept.core.mo
kitconcept/core/locales/en/LC_MESSAGES/kitconcept.core.po
kitconcept/core/profiles/base/actions.xml
kitconcept/core/profiles/base/browserlayer.xml
kitconcept/core/profiles/base/catalog.xml
kitconcept/core/profiles/base/componentregistry.xml
kitconcept/core/profiles/base/contenttyperegistry.xml
kitconcept/core/profiles/base/controlpanel.xml
kitconcept/core/profiles/base/mailhost.xml
kitconcept/core/profiles/base/memberdata_properties.xml
kitconcept/core/profiles/base/metadata.xml
kitconcept/core/profiles/base/properties.xml
kitconcept/core/profiles/base/rolemap.xml
kitconcept/core/profiles/base/skins.xml
kitconcept/core/profiles/base/toolset.xml
kitconcept/core/profiles/base/types.xml
kitconcept/core/profiles/base/viewlets.xml
kitconcept/core/profiles/base/workflows.xml
kitconcept/core/profiles/base/types/Plone_Site.xml
kitconcept/core/profiles/base/types/TempFolder.xml
kitconcept_core-1.0.6.dist-info/METADATA
kitconcept_core-1.0.6.dist-info/WHEEL
kitconcept_core-1.0.6.dist-info/entry_points.txt
kitconcept_core-1.0.6.dist-info/licenses/LICENSE.GPL
kitconcept_core-1.0.6.dist-info/licenses/LICENSE.md
kitconcept_core-1.0.6.dist-info/RECORD
