Metadata-Version: 2.4
Name: kitconcept.core
Version: 1.0.6
Summary: Core setup for kitconcept GmbH distributions built on top of Plone
Project-URL: Homepage, https://github.com/kitconcept/kitconcept-core
Project-URL: PyPI, https://pypi.org/project/kitconcept.core
Project-URL: Source, https://github.com/kitconcept/kitconcept-core
Project-URL: Tracker, https://github.com/kitconcept/kitconcept-core/issues
Author-email: kitconcept GmbH <contact@kitconcept.com>
License-Expression: GPL-2.0-only
License-File: LICENSE.GPL
License-File: LICENSE.md
Keywords: CMS,Plone,Python
Classifier: Development Status :: 3 - Alpha
Classifier: Environment :: Web Environment
Classifier: Framework :: Plone
Classifier: Framework :: Plone :: 6.1
Classifier: Framework :: Plone :: Addon
Classifier: License :: OSI Approved :: GNU General Public License v2 (GPLv2)
Classifier: Operating System :: OS Independent
Classifier: Programming Language :: Python
Classifier: Programming Language :: Python :: 3.12
Requires-Python: ==3.12.*
Requires-Dist: collective-honeypot
Requires-Dist: collective-person==1.0.0b4
Requires-Dist: collective-volto-formsupport==3.2.3
Requires-Dist: kitconcept-voltolighttheme<8.0.0,>=7.6.5
Requires-Dist: plone-api
Requires-Dist: plone-distribution
Requires-Dist: products-cmfplone==6.1.3
Provides-Extra: test
Requires-Dist: horse-with-no-namespace; extra == 'test'
Requires-Dist: plone-app-testing; extra == 'test'
Requires-Dist: plone-restapi[test]; extra == 'test'
Requires-Dist: pytest; extra == 'test'
Requires-Dist: pytest-cov; extra == 'test'
Requires-Dist: pytest-plone>=1.0.0a1; extra == 'test'
